kagent/__init__.py
kagent/cli.py
kagent/py.typed
kagent/tools/__init__.py
kagent/tools/_utils.py
kagent/tools/common/shell.py
kagent/tools/docs/__init__.py
kagent/tools/docs/query_documentation.py
kagent/tools/istio/__init__.py
kagent/tools/istio/_istio_crds.py
kagent/tools/istio/_istioctl.py
kagent/tools/istio/prompts/__init__.py
kagent/tools/istio/prompts/auth_policy.py
kagent/tools/istio/prompts/base.py
kagent/tools/istio/prompts/gateway.py
kagent/tools/istio/prompts/peer_auth.py
kagent/tools/istio/prompts/virtual_service.py
kagent/tools/k8s/__init__.py
kagent/tools/k8s/_kubectl.py
kagent/tools/prometheus/__init__.py
kagent/tools/prometheus/_prometheus.py
kagent-0.1.0.dist-info/METADATA
kagent-0.1.0.dist-info/WHEEL
kagent-0.1.0.dist-info/entry_points.txt
kagent-0.1.0.dist-info/RECORD
